LICENSE.txt
README.md
setup.py
netmask/__init__.py
netmask/netmaskc.py
netmask/netmasks.py
netmask.egg-info/PKG-INFO
netmask.egg-info/SOURCES.txt
netmask.egg-info/dependency_links.txt
netmask.egg-info/entry_points.txt
netmask.egg-info/top_level.txt
netmask/client/__init__.py
netmask/client/main.py
netmask/impl/__init__.py
netmask/impl/packets.py
netmask/server/__init__.py
netmask/server/main.py
netmask/utils/__init__.py
netmask/utils/encryption.py