Metadata-Version: 2.1
Name: netmask
Version: 0.1.0
Summary: A TCP/UDP self-hostable reverse proxy server that supports IPv4 and IPv6
Author: Joseph
Author-email: josephdove@proton.me
Classifier: Programming Language :: Python :: 3.6
Classifier: License :: OSI Approved :: MIT License
Classifier: Operating System :: OS Independent
Requires-Python: >=3.6
License-File: LICENSE.txt
